{
  "results": [
    {
      "wrapperType": "track",
      "kind": "song",
      "artistId": 1648625793,
      "collectionId": 1895175968,
      "trackId": 6763132041,
      "artistName": "LONOWN & riserayss",
      "collectionName": "worry (Instrumental edition) - Single",
      "trackName": "worry (Instrumental Ultra Slowed)",
      "collectionCensoredName": "worry (Instrumental edition) - Single",
      "trackCensoredName": "worry (Instrumental Ultra Slowed)",
      "artistViewUrl": "https://music.apple.com/us/artist/lonown/1648625793?uo=4",
      "collectionViewUrl": "https://music.apple.com/us/album/worry-instrumental-ultra-slowed/1895175968?i=6763132041&uo=4",
      "trackViewUrl": "https://music.apple.com/us/album/worry-instrumental-ultra-slowed/1895175968?i=6763132041&uo=4",
      "previewUrl": "https://audio-ssl.itunes.apple.com/itunes-assets/AudioPreview221/v4/5c/e6/06/5ce60653-6b55-97b3-a923-c2e187b85c2e/mzaf_4436632446910296959.plus.aac.p.m4a",
      "artworkUrl30": "https://is1-ssl.mzstatic.com/image/thumb/Music221/v4/8a/df/59/8adf5988-95e3-2e34-028f-b7cd9f931555/cover.jpg/30x30bb.jpg",
      "artworkUrl60": "https://is1-ssl.mzstatic.com/image/thumb/Music221/v4/8a/df/59/8adf5988-95e3-2e34-028f-b7cd9f931555/cover.jpg/60x60bb.jpg",
      "artworkUrl100": "https://is1-ssl.mzstatic.com/image/thumb/Music221/v4/8a/df/59/8adf5988-95e3-2e34-028f-b7cd9f931555/cover.jpg/100x100bb.jpg",
      "releaseDate": "2026-04-24T12:00:00Z",
      "collectionExplicitness": "notExplicit",
      "trackExplicitness": "notExplicit",
      "discCount": 1,
      "discNumber": 1,
      "trackCount": 3,
      "trackNumber": 3,
      "trackTimeMillis": 257942,
      "country": "USA",
      "currency": "USD",
      "primaryGenreName": "Electronic",
      "isStreamable": true
    },
    {
      "wrapperType": "track",
      "kind": "song",
      "artistId": 1648625793,
      "collectionId": 1838749429,
      "trackId": 1838749858,
      "artistName": "LONOWN & riserayss",
      "collectionName": "worry - Single",
      "trackName": "worry (Slowed)",
      "collectionCensoredName": "worry - Single",
      "trackCensoredName": "worry (Slowed)",
      "artistViewUrl": "https://music.apple.com/us/artist/lonown/1648625793?uo=4",
      "collectionViewUrl": "https://music.apple.com/us/album/worry-slowed/1838749429?i=1838749858&uo=4",
      "trackViewUrl": "https://music.apple.com/us/album/worry-slowed/1838749429?i=1838749858&uo=4",
      "previewUrl": "https://audio-ssl.itunes.apple.com/itunes-assets/AudioPreview211/v4/e9/da/a6/e9daa603-e39c-16e8-4909-52a6ef3d8773/mzaf_10173837896479847523.plus.aac.p.m4a",
      "artworkUrl30": "https://is1-ssl.mzstatic.com/image/thumb/Music211/v4/5c/27/d6/5c27d681-1fa2-55b6-9152-f036e2bb80c3/cover.jpg/30x30bb.jpg",
      "artworkUrl60": "https://is1-ssl.mzstatic.com/image/thumb/Music211/v4/5c/27/d6/5c27d681-1fa2-55b6-9152-f036e2bb80c3/cover.jpg/60x60bb.jpg",
      "artworkUrl100": "https://is1-ssl.mzstatic.com/image/thumb/Music211/v4/5c/27/d6/5c27d681-1fa2-55b6-9152-f036e2bb80c3/cover.jpg/100x100bb.jpg",
      "releaseDate": "2025-10-10T12:00:00Z",
      "collectionExplicitness": "notExplicit",
      "trackExplicitness": "notExplicit",
      "discCount": 1,
      "discNumber": 1,
      "trackCount": 2,
      "trackNumber": 2,
      "trackTimeMillis": 201909,
      "country": "USA",
      "currency": "USD",
      "primaryGenreName": "Electronic",
      "isStreamable": true
    },
    {
      "wrapperType": "track",
      "kind": "song",
      "artistId": 1648625793,
      "collectionId": 1815479608,
      "trackId": 1815479623,
      "artistName": "LONOWN & riserayss",
      "collectionName": "starly (Ultra Slowed) - Single",
      "trackName": "starly (Ultra Slowed)",
      "collectionCensoredName": "starly (Ultra Slowed) - Single",
      "trackCensoredName": "starly (Ultra Slowed)",
      "artistViewUrl": "https://music.apple.com/us/artist/lonown/1648625793?uo=4",
      "collectionViewUrl": "https://music.apple.com/us/album/starly-ultra-slowed/1815479608?i=1815479623&uo=4",
      "trackViewUrl": "https://music.apple.com/us/album/starly-ultra-slowed/1815479608?i=1815479623&uo=4",
      "previewUrl": "https://audio-ssl.itunes.apple.com/itunes-assets/AudioPreview211/v4/04/20/ab/0420abd1-c56b-c26a-983d-0fa04b3e34b9/mzaf_10438430662618285321.plus.aac.p.m4a",
      "artworkUrl30": "https://is1-ssl.mzstatic.com/image/thumb/Music211/v4/8b/33/61/8b336104-7f34-d39a-dae4-b9e63418e3aa/cover.jpg/30x30bb.jpg",
      "artworkUrl60": "https://is1-ssl.mzstatic.com/image/thumb/Music211/v4/8b/33/61/8b336104-7f34-d39a-dae4-b9e63418e3aa/cover.jpg/60x60bb.jpg",
      "artworkUrl100": "https://is1-ssl.mzstatic.com/image/thumb/Music211/v4/8b/33/61/8b336104-7f34-d39a-dae4-b9e63418e3aa/cover.jpg/100x100bb.jpg",
      "collectionPrice": 1.29,
      "trackPrice": 1.29,
      "releaseDate": "2023-10-24T12:00:00Z",
      "collectionExplicitness": "notExplicit",
      "trackExplicitness": "notExplicit",
      "discCount": 1,
      "discNumber": 1,
      "trackCount": 1,
      "trackNumber": 1,
      "trackTimeMillis": 224793,
      "country": "USA",
      "currency": "USD",
      "primaryGenreName": "Electronic",
      "isStreamable": true
    },
    {
      "wrapperType": "track",
      "kind": "song",
      "artistId": 1306021949,
      "collectionId": 1702842278,
      "trackId": 1702842541,
      "artistName": "akiaura, LONOWN & STM",
      "collectionName": "Sleepwalker (Ultra Slowed & Reverb) - Single",
      "trackName": "Sleepwalker (Ultra Slowed & Reverb)",
      "collectionCensoredName": "Sleepwalker (Ultra Slowed & Reverb) - Single",
      "trackCensoredName": "Sleepwalker (Ultra Slowed & Reverb)",
      "artistViewUrl": "https://music.apple.com/us/artist/akiaura/1306021949?uo=4",
      "collectionViewUrl": "https://music.apple.com/us/album/sleepwalker-ultra-slowed-reverb/1702842278?i=1702842541&uo=4",
      "trackViewUrl": "https://music.apple.com/us/album/sleepwalker-ultra-slowed-reverb/1702842278?i=1702842541&uo=4",
      "previewUrl": "https://audio-ssl.itunes.apple.com/itunes-assets/AudioPreview221/v4/1e/93/8c/1e938c57-6ae8-a871-cd9b-461d9bb74edd/mzaf_7165356601224140043.plus.aac.p.m4a",
      "artworkUrl30": "https://is1-ssl.mzstatic.com/image/thumb/Music116/v4/97/d0/ac/97d0acd3-767c-04d9-2f93-aaa75bf545d5/cover.jpg/30x30bb.jpg",
      "artworkUrl60": "https://is1-ssl.mzstatic.com/image/thumb/Music116/v4/97/d0/ac/97d0acd3-767c-04d9-2f93-aaa75bf545d5/cover.jpg/60x60bb.jpg",
      "artworkUrl100": "https://is1-ssl.mzstatic.com/image/thumb/Music116/v4/97/d0/ac/97d0acd3-767c-04d9-2f93-aaa75bf545d5/cover.jpg/100x100bb.jpg",
      "collectionPrice": 1.29,
      "trackPrice": 1.29,
      "releaseDate": "2023-09-15T12:00:00Z",
      "collectionExplicitness": "notExplicit",
      "trackExplicitness": "notExplicit",
      "discCount": 1,
      "discNumber": 1,
      "trackCount": 1,
      "trackNumber": 1,
      "trackTimeMillis": 317563,
      "country": "USA",
      "currency": "USD",
      "primaryGenreName": "Electronic",
      "isStreamable": true
    },
    {
      "wrapperType": "track",
      "kind": "song",
      "artistId": 1648625793,
      "collectionId": 1895175968,
      "trackId": 6763132040,
      "artistName": "LONOWN & riserayss",
      "collectionName": "worry (Instrumental edition) - Single",
      "trackName": "worry (Instrumental Slowed)",
      "collectionCensoredName": "worry (Instrumental edition) - Single",
      "trackCensoredName": "worry (Instrumental Slowed)",
      "artistViewUrl": "https://music.apple.com/us/artist/lonown/1648625793?uo=4",
      "collectionViewUrl": "https://music.apple.com/us/album/worry-instrumental-slowed/1895175968?i=6763132040&uo=4",
      "trackViewUrl": "https://music.apple.com/us/album/worry-instrumental-slowed/1895175968?i=6763132040&uo=4",
      "previewUrl": "https://audio-ssl.itunes.apple.com/itunes-assets/AudioPreview211/v4/0d/10/fb/0d10fb82-d588-f2e7-a480-1b369220841e/mzaf_11656489326699716174.plus.aac.p.m4a",
      "artworkUrl30": "https://is1-ssl.mzstatic.com/image/thumb/Music221/v4/8a/df/59/8adf5988-95e3-2e34-028f-b7cd9f931555/cover.jpg/30x30bb.jpg",
      "artworkUrl60": "https://is1-ssl.mzstatic.com/image/thumb/Music221/v4/8a/df/59/8adf5988-95e3-2e34-028f-b7cd9f931555/cover.jpg/60x60bb.jpg",
      "artworkUrl100": "https://is1-ssl.mzstatic.com/image/thumb/Music221/v4/8a/df/59/8adf5988-95e3-2e34-028f-b7cd9f931555/cover.jpg/100x100bb.jpg",
      "releaseDate": "2026-04-24T12:00:00Z",
      "collectionExplicitness": "notExplicit",
      "trackExplicitness": "notExplicit",
      "discCount": 1,
      "discNumber": 1,
      "trackCount": 3,
      "trackNumber": 2,
      "trackTimeMillis": 201442,
      "country": "USA",
      "currency": "USD",
      "primaryGenreName": "Electronic",
      "isStreamable": true
    },
    {
      "wrapperType": "track",
      "kind": "song",
      "artistId": 1648625793,
      "collectionId": 1838749429,
      "trackId": 1838749852,
      "artistName": "LONOWN & riserayss",
      "collectionName": "worry - Single",
      "trackName": "worry",
      "collectionCensoredName": "worry - Single",
      "trackCensoredName": "worry",
      "artistViewUrl": "https://music.apple.com/us/artist/lonown/1648625793?uo=4",
      "collectionViewUrl": "https://music.apple.com/us/album/worry/1838749429?i=1838749852&uo=4",
      "trackViewUrl": "https://music.apple.com/us/album/worry/1838749429?i=1838749852&uo=4",
      "previewUrl": "https://audio-ssl.itunes.apple.com/itunes-assets/AudioPreview221/v4/d3/ff/71/d3ff712c-9a7e-e33d-1adf-3d2c4cbb1314/mzaf_6066214818334587858.plus.aac.p.m4a",
      "artworkUrl30": "https://is1-ssl.mzstatic.com/image/thumb/Music211/v4/5c/27/d6/5c27d681-1fa2-55b6-9152-f036e2bb80c3/cover.jpg/30x30bb.jpg",
      "artworkUrl60": "https://is1-ssl.mzstatic.com/image/thumb/Music211/v4/5c/27/d6/5c27d681-1fa2-55b6-9152-f036e2bb80c3/cover.jpg/60x60bb.jpg",
      "artworkUrl100": "https://is1-ssl.mzstatic.com/image/thumb/Music211/v4/5c/27/d6/5c27d681-1fa2-55b6-9152-f036e2bb80c3/cover.jpg/100x100bb.jpg",
      "releaseDate": "2025-10-10T12:00:00Z",
      "collectionExplicitness": "notExplicit",
      "trackExplicitness": "notExplicit",
      "discCount": 1,
      "discNumber": 1,
      "trackCount": 2,
      "trackNumber": 1,
      "trackTimeMillis": 180716,
      "country": "USA",
      "currency": "USD",
      "primaryGenreName": "Electronic",
      "isStreamable": true
    },
    {
      "wrapperType": "track",
      "kind": "song",
      "artistId": 1306021949,
      "collectionId": 1697346417,
      "trackId": 1697346422,
      "artistName": "akiaura, LONOWN & STM",
      "collectionName": "Sleepwalker (Slowed) - Single",
      "trackName": "Sleepwalker (Slowed)",
      "collectionCensoredName": "Sleepwalker (Slowed) - Single",
      "trackCensoredName": "Sleepwalker (Slowed)",
      "artistViewUrl": "https://music.apple.com/us/artist/akiaura/1306021949?uo=4",
      "collectionViewUrl": "https://music.apple.com/us/album/sleepwalker-slowed/1697346417?i=1697346422&uo=4",
      "trackViewUrl": "https://music.apple.com/us/album/sleepwalker-slowed/1697346417?i=1697346422&uo=4",
      "previewUrl": "https://audio-ssl.itunes.apple.com/itunes-assets/AudioPreview221/v4/84/6d/78/846d7831-5c4a-b1f9-b53c-65e7cb95cc98/mzaf_1721979667938068681.plus.aac.p.m4a",
      "artworkUrl30": "https://is1-ssl.mzstatic.com/image/thumb/Music116/v4/a4/49/86/a4498628-fb97-1557-3c68-cfa28547cf8d/cover.jpg/30x30bb.jpg",
      "artworkUrl60": "https://is1-ssl.mzstatic.com/image/thumb/Music116/v4/a4/49/86/a4498628-fb97-1557-3c68-cfa28547cf8d/cover.jpg/60x60bb.jpg",
      "artworkUrl100": "https://is1-ssl.mzstatic.com/image/thumb/Music116/v4/a4/49/86/a4498628-fb97-1557-3c68-cfa28547cf8d/cover.jpg/100x100bb.jpg",
      "collectionPrice": 1.29,
      "trackPrice": 1.29,
      "releaseDate": "2023-07-14T12:00:00Z",
      "collectionExplicitness": "notExplicit",
      "trackExplicitness": "notExplicit",
      "discCount": 1,
      "discNumber": 1,
      "trackCount": 1,
      "trackNumber": 1,
      "trackTimeMillis": 258009,
      "country": "USA",
      "currency": "USD",
      "primaryGenreName": "Electronic",
      "isStreamable": true
    },
    {
      "wrapperType": "track",
      "kind": "song",
      "artistId": 1895277271,
      "collectionId": 6773097925,
      "trackId": 6773097926,
      "artistName": "Gorav CJ",
      "collectionName": "worry ultra slowed - Single",
      "trackName": "worry ultra slowed",
      "collectionCensoredName": "worry ultra slowed - Single",
      "trackCensoredName": "worry ultra slowed",
      "artistViewUrl": "https://music.apple.com/us/artist/gorav-cj/1895277271?uo=4",
      "collectionViewUrl": "https://music.apple.com/us/album/worry-ultra-slowed/6773097925?i=6773097926&uo=4",
      "trackViewUrl": "https://music.apple.com/us/album/worry-ultra-slowed/6773097925?i=6773097926&uo=4",
      "previewUrl": "https://audio-ssl.itunes.apple.com/itunes-assets/AudioPreview221/v4/a3/71/d5/a371d504-566c-e9cb-bdd6-22ddadb5b88c/mzaf_2735193091613569976.plus.aac.p.m4a",
      "artworkUrl30": "https://is1-ssl.mzstatic.com/image/thumb/Music221/v4/8c/1c/6f/8c1c6f25-4587-f7f0-f837-659429a2786d/7333583544672.jpg/30x30bb.jpg",
      "artworkUrl60": "https://is1-ssl.mzstatic.com/image/thumb/Music221/v4/8c/1c/6f/8c1c6f25-4587-f7f0-f837-659429a2786d/7333583544672.jpg/60x60bb.jpg",
      "artworkUrl100": "https://is1-ssl.mzstatic.com/image/thumb/Music221/v4/8c/1c/6f/8c1c6f25-4587-f7f0-f837-659429a2786d/7333583544672.jpg/100x100bb.jpg",
      "collectionPrice": 0.99,
      "trackPrice": 0.99,
      "releaseDate": "2026-05-25T12:00:00Z",
      "collectionExplicitness": "notExplicit",
      "trackExplicitness": "notExplicit",
      "discCount": 1,
      "discNumber": 1,
      "trackCount": 1,
      "trackNumber": 1,
      "trackTimeMillis": 162128,
      "country": "USA",
      "currency": "USD",
      "primaryGenreName": "Indie Pop",
      "isStreamable": true
    },
    {
      "wrapperType": "track",
      "kind": "song",
      "artistId": 1760551007,
      "collectionId": 6768386824,
      "trackId": 6768386829,
      "artistName": "LVSTWXRLD",
      "collectionName": "Worry - EP",
      "trackName": "Worry (Trending Ultra Slowed)",
      "collectionCensoredName": "Worry - EP",
      "trackCensoredName": "Worry (Trending Ultra Slowed)",
      "artistViewUrl": "https://music.apple.com/us/artist/lvstwxrld/1760551007?uo=4",
      "collectionViewUrl": "https://music.apple.com/us/album/worry-trending-ultra-slowed/6768386824?i=6768386829&uo=4",
      "trackViewUrl": "https://music.apple.com/us/album/worry-trending-ultra-slowed/6768386824?i=6768386829&uo=4",
      "previewUrl": "https://audio-ssl.itunes.apple.com/itunes-assets/AudioPreview221/v4/a0/49/fb/a049fb6a-9177-3aab-a206-bb5d637c510a/mzaf_9043064556863670546.plus.aac.p.m4a",
      "artworkUrl30": "https://is1-ssl.mzstatic.com/image/thumb/Music211/v4/d1/19/61/d1196147-ff90-4966-034a-7d1a3f9c691b/artwork.jpg/30x30bb.jpg",
      "artworkUrl60": "https://is1-ssl.mzstatic.com/image/thumb/Music211/v4/d1/19/61/d1196147-ff90-4966-034a-7d1a3f9c691b/artwork.jpg/60x60bb.jpg",
      "artworkUrl100": "https://is1-ssl.mzstatic.com/image/thumb/Music211/v4/d1/19/61/d1196147-ff90-4966-034a-7d1a3f9c691b/artwork.jpg/100x100bb.jpg",
      "collectionPrice": 3.96,
      "trackPrice": 0.99,
      "releaseDate": "2026-05-08T12:00:00Z",
      "collectionExplicitness": "notExplicit",
      "trackExplicitness": "notExplicit",
      "discCount": 1,
      "discNumber": 1,
      "trackCount": 4,
      "trackNumber": 4,
      "trackTimeMillis": 229045,
      "country": "USA",
      "currency": "USD",
      "primaryGenreName": "Dance",
      "isStreamable": true
    },
    {
      "wrapperType": "track",
      "kind": "song",
      "artistId": 1699869518,
      "collectionId": 1881200896,
      "trackId": 1881200898,
      "artistName": "SXULXEMPINESS",
      "collectionName": "worry - Single",
      "trackName": "worry (Slowed)",
      "collectionCensoredName": "worry - Single",
      "trackCensoredName": "worry (Slowed)",
      "artistViewUrl": "https://music.apple.com/us/artist/sxulxempiness/1699869518?uo=4",
      "collectionViewUrl": "https://music.apple.com/us/album/worry-slowed/1881200896?i=1881200898&uo=4",
      "trackViewUrl": "https://music.apple.com/us/album/worry-slowed/1881200896?i=1881200898&uo=4",
      "previewUrl": "https://audio-ssl.itunes.apple.com/itunes-assets/AudioPreview211/v4/04/b8/f9/04b8f93d-f8b6-c14c-713c-ef4e84b66a08/mzaf_4653127743468502146.plus.aac.p.m4a",
      "artworkUrl30": "https://is1-ssl.mzstatic.com/image/thumb/Music211/v4/b5/e4/4a/b5e44ac8-fd4e-55cd-c065-3a10032483cc/cover.png/30x30bb.jpg",
      "artworkUrl60": "https://is1-ssl.mzstatic.com/image/thumb/Music211/v4/b5/e4/4a/b5e44ac8-fd4e-55cd-c065-3a10032483cc/cover.png/60x60bb.jpg",
      "artworkUrl100": "https://is1-ssl.mzstatic.com/image/thumb/Music211/v4/b5/e4/4a/b5e44ac8-fd4e-55cd-c065-3a10032483cc/cover.png/100x100bb.jpg",
      "collectionPrice": 1.99,
      "trackPrice": 1.29,
      "releaseDate": "2026-03-06T12:00:00Z",
      "collectionExplicitness": "notExplicit",
      "trackExplicitness": "notExplicit",
      "discCount": 1,
      "discNumber": 1,
      "trackCount": 3,
      "trackNumber": 2,
      "trackTimeMillis": 118202,
      "country": "USA",
      "currency": "USD",
      "primaryGenreName": "Ambient",
      "isStreamable": true
    }
  ],
  "query": {
    "title": "worry",
    "artist": "ultra slowed - LONOWN"
  }
}